api_marketplace_client/__init__.py
api_marketplace_client/base.py
api_marketplace_client/exceptions.py
api_marketplace_client/async_/__init__.py
api_marketplace_client/async_/client.py
api_marketplace_client/sync/__init__.py
api_marketplace_client/sync/client.py
api_marketplace_client-1.0.0.8.dist-info/licenses/LICENSE
tests/__init__.py
tests/test_client.py
api_marketplace_client-1.0.0.8.dist-info/METADATA
api_marketplace_client-1.0.0.8.dist-info/WHEEL
api_marketplace_client-1.0.0.8.dist-info/top_level.txt
api_marketplace_client-1.0.0.8.dist-info/RECORD
